aws_simple/__init__.py
aws_simple/_clients.py
aws_simple/bedrock.py
aws_simple/config.py
aws_simple/exceptions.py
aws_simple/s3.py
aws_simple/textract.py
aws_simple/_parsers/__init__.py
aws_simple/_parsers/textract_parser.py
aws_simple/models/__init__.py
aws_simple/models/textract.py
aws_simple-0.1.1b2.dist-info/METADATA
aws_simple-0.1.1b2.dist-info/WHEEL
aws_simple-0.1.1b2.dist-info/licenses/LICENSE
aws_simple-0.1.1b2.dist-info/RECORD
