Metadata-Version: 2.4
Name: aws-simple
Version: 0.1.1b2
Summary: A clean, simple wrapper around AWS services (S3, Textract, Bedrock)
Project-URL: Homepage, https://github.com/maxg56/aws-toolkit-py
Project-URL: Repository, https://github.com/maxg56/aws-toolkit-py
Project-URL: Issues, https://github.com/maxg56/aws-toolkit-py/issues
License: MIT
License-File: LICENSE
Keywords: aws,bedrock,boto3,s3,textract,wrapper
Classifier: Development Status :: 3 - Alpha
Classifier: Intended Audience :: Developers
Classifier: License :: OSI Approved :: MIT License
Classifier: Programming Language :: Python :: 3.10
Classifier: Programming Language :: Python :: 3.11
Classifier: Programming Language :: Python :: 3.12
Classifier: Programming Language :: Python :: 3.13
Classifier: Programming Language :: Python :: 3.14
Requires-Python: >=3.10
Requires-Dist: boto3>=1.34.0
Requires-Dist: python-dotenv>=1.0.0
Provides-Extra: dev
Requires-Dist: black>=24.0.0; extra == 'dev'
Requires-Dist: boto3-stubs[bedrock,s3,textract]>=1.34.0; extra == 'dev'
Requires-Dist: mypy>=1.8.0; extra == 'dev'
Requires-Dist: pytest-cov>=4.1.0; extra == 'dev'
Requires-Dist: pytest>=7.4.0; extra == 'dev'
Requires-Dist: ruff>=0.1.0; extra == 'dev'
